{
    "courses":[
    {
        "id": 1,
        "name": "Angular",
        "imgPath": "../../assets/img/angular.png",
        "start_date": "2020-10-11",
        "price": 30000,
        "duration": 25,
        "rating": 4.367,
        "students": 20000
    },
    {
        "id": 2,
        "name": "React",
        "imgPath": "../../assets/img/react.png",
        "start_date": "2020-10-11",
        "price": 25000,
        "duration": 30,
        "rating": 4.677,
        "students": 15000
    }
  ]
}
